keygen/__init__.py
keygen/__main__.py
keygen/gui.py
keygen/keys.py
keygen/data/images/icon.png
keygen/data/images/license_key.png
keygen/data/images/logo.png
keygen/data/images/main.png
keygen/data/images/new_rsa.png
keygen/data/ui/about.ui
keygen/data/ui/license_key.ui
keygen/data/ui/main.ui
keygen/data/ui/new_rsa.ui
keygen_yocto-2.0.0.dist-info/LICENSE.txt
keygen_yocto-2.0.0.dist-info/METADATA
keygen_yocto-2.0.0.dist-info/WHEEL
keygen_yocto-2.0.0.dist-info/entry_points.txt
keygen_yocto-2.0.0.dist-info/top_level.txt
keygen_yocto-2.0.0.dist-info/RECORD
