Metadata-Version: 2.1
Name: keygen-yocto
Version: 2.0.0
Summary: A simple tool to generate and verify license keys for your app.
Home-page: https://github.com/yoctosoft-ltd/keygen
Author: Yoctosoft
Author-email: info@yoctosoft.co.za
License: UNKNOWN
Keywords: license key generator
Platform: UNKNOWN
Classifier: Development Status :: 5 - Production/Stable
Classifier: Environment :: MacOS X
Classifier: Environment :: Win32 (MS Windows)
Classifier: Environment :: X11 Applications :: Qt
Classifier: Intended Audience :: Customer Service
Classifier: Intended Audience :: Developers
Classifier: License :: OSI Approved :: GNU General Public License (GPL)
Classifier: Natural Language :: English
Classifier: Operating System :: MacOS
Classifier: Operating System :: Microsoft :: Windows
Classifier: Operating System :: POSIX
Classifier: Programming Language :: Python :: 3.8
Classifier: Topic :: Security
Classifier: Topic :: Utilities
Requires-Python: >=3.8
Requires-Dist: PySide2
Requires-Dist: rsa
